bufr2geojson/__init__.py
bufr2geojson/cli.py
bufr2geojson/resources/031021.json
bufr2geojson/resources/schemas/wccdm-obs.json
bufr2geojson-0.7.1.dist-info/LICENSE
bufr2geojson-0.7.1.dist-info/METADATA
bufr2geojson-0.7.1.dist-info/WHEEL
bufr2geojson-0.7.1.dist-info/entry_points.txt
bufr2geojson-0.7.1.dist-info/top_level.txt
bufr2geojson-0.7.1.dist-info/RECORD
