Metadata-Version: 2.1
Name: bufr2geojson
Version: 0.7.1
Summary: Configurable module to convert data from CSV to WMO BUFR format
Home-page: https://github.com/World-Meteorological-Organization/bufr2geojson
Author: David I. Berry
Author-email: DBerry@wmo.int
Maintainer: David I. Berry
Maintainer-email: DBerry@wmo.int
License: Apache Software License
Keywords: WMO BUFR csv encoding weather observations
Platform: all
Classifier: Development Status :: 3 - Alpha
Classifier: Environment :: Console
Classifier: Intended Audience :: Developers
Classifier: Intended Audience :: Science/Research
Classifier: License :: OSI Approved :: Apache Software License
Classifier: Operating System :: OS Independent
Classifier: Programming Language :: Python
Classifier: Topic :: Scientific/Engineering
License-File: LICENSE
Requires-Dist: attrs (>=22.2.0)
Requires-Dist: cfunits
Requires-Dist: click
Requires-Dist: eccodes
Requires-Dist: jsonschema
Requires-Dist: jsonpath-ng
Requires-Dist: pyoscar
Requires-Dist: PyYAML
